serial_dashboard/__init__.py
serial_dashboard/boards.py
serial_dashboard/callbacks.py
serial_dashboard/comms.py
serial_dashboard/dashboard.py
serial_dashboard/parsers.py
serial_dashboard/scripts/__init__.py
serial_dashboard/scripts/launchscript.py
serial_dashboard/scripts/serialdashboard.py
serial_dashboard-0.1.2.dist-info/LICENSE
serial_dashboard-0.1.2.dist-info/METADATA
serial_dashboard-0.1.2.dist-info/WHEEL
serial_dashboard-0.1.2.dist-info/entry_points.txt
serial_dashboard-0.1.2.dist-info/top_level.txt
serial_dashboard-0.1.2.dist-info/RECORD
