Metadata-Version: 2.1
Name: serial-dashboard
Version: 0.1.2
Summary: Bokeh-based serial dashboard.
Home-page: https://github.com/justinbois/serial-dashboard
Download-URL: https://github.com/justinbois/serial-dashboard/tarball/0.1.2
Author: Justin Bois
Author-email: bois@caltech.edu
License: BSD
Classifier: Development Status :: 3 - Alpha
Classifier: Intended Audience :: Science/Research
Classifier: Programming Language :: Python :: 3
License-File: LICENSE
Requires-Dist: pyserial
Requires-Dist: numpy
Requires-Dist: pandas
Requires-Dist: bokeh
Requires-Dist: Click
